bluetooth/__init__.py
bluetooth/_msbt.cp37-win_amd64.pyd
bluetooth/ble.py
bluetooth/bluez.py
bluetooth/btcommon.py
bluetooth/msbt.py
bluetooth/osx.py
bluetooth/widcomm.py
pybluez22-1.0.dist-info/COPYING
pybluez22-1.0.dist-info/METADATA
pybluez22-1.0.dist-info/WHEEL
pybluez22-1.0.dist-info/eager_resources.txt
pybluez22-1.0.dist-info/top_level.txt
pybluez22-1.0.dist-info/zip-safe
pybluez22-1.0.dist-info/RECORD
